padio.py
padio-1.0.1.dist-info/LICENSE
padio-1.0.1.dist-info/METADATA
padio-1.0.1.dist-info/WHEEL
padio-1.0.1.dist-info/entry_points.txt
padio-1.0.1.dist-info/top_level.txt
padio-1.0.1.dist-info/RECORD
