Metadata-Version: 2.1
Name: padio
Version: 1.0.1
Summary: Zero pad numeric filenames
Home-page: https://git.iamthefij.com/iamthefij/padio.git
Author: iamthefij
Author-email: ian@iamthefij.com
License: UNKNOWN
Download-URL: https://git.iamthefij.com/iamthefij/padio/releases
Platform: UNKNOWN
Classifier: License :: OSI Approved :: MIT License
Classifier: Programming Language :: Python :: 3 :: Only
Classifier: Programming Language :: Python :: 3
Classifier: Programming Language :: Python :: 3.7
Classifier: Programming Language :: Python :: 3.8
Classifier: Programming Language :: Python :: 3.9
